{
  "total_items": 407,
  "grounded_items": 278,
  "ungrounded": [
    {
      "word": "офіційним",
      "exercise_type": "true-false",
      "context": "Віддієслівний іменник допомагає зробити текст більш офіційни"
    },
    {
      "word": "фразі",
      "exercise_type": "true-false",
      "context": "У фразі «якісна освіта» ми фокусуємо увагу на результаті, а "
    },
    {
      "word": "процесі",
      "exercise_type": "true-false",
      "context": "У фразі «якісна освіта» ми фокусуємо увагу на результаті, а "
    },
    {
      "word": "використовувати",
      "exercise_type": "true-false",
      "context": "Ми повинні використовувати віддієслівні іменники якомога час"
    },
    {
      "word": "щоденних",
      "exercise_type": "true-false",
      "context": "Ми повинні використовувати віддієслівні іменники якомога час"
    },
    {
      "word": "розмовах",
      "exercise_type": "true-false",
      "context": "Ми повинні використовувати віддієслівні іменники якомога час"
    },
    {
      "word": "друзями",
      "exercise_type": "true-false",
      "context": "Ми повинні використовувати віддієслівні іменники якомога час"
    },
    {
      "word": "звертатися",
      "exercise_type": "match-up",
      "context": "звертатися"
    },
    {
      "word": "корисний",
      "exercise_type": "fill-in",
      "context": "Швидкий _____ дуже корисний для серця."
    },
    {
      "word": "зайняв",
      "exercise_type": "fill-in",
      "context": "Цей _____ ключів зайняв десять хвилин."
    },
    {
      "word": "хвилин",
      "exercise_type": "fill-in",
      "context": "Цей _____ ключів зайняв десять хвилин."
    },
    {
      "word": "шукання",
      "exercise_type": "fill-in",
      "context": "шукання"
    },
    {
      "word": "шукати",
      "exercise_type": "fill-in",
      "context": "шукати"
    },
    {
      "word": "справжній",
      "exercise_type": "fill-in",
      "context": "Це справжній _____ для нашої команди."
    },
    {
      "word": "викликання",
      "exercise_type": "fill-in",
      "context": "викликання"
    },
    {
      "word": "професії",
      "exercise_type": "fill-in",
      "context": "Твій _____ професії був абсолютно правильним."
    },
    {
      "word": "був",
      "exercise_type": "fill-in",
      "context": "Твій _____ професії був абсолютно правильним."
    },
    {
      "word": "правильним",
      "exercise_type": "fill-in",
      "context": "Твій _____ професії був абсолютно правильним."
    },
    {
      "word": "вибирання",
      "exercise_type": "fill-in",
      "context": "вибирання"
    },
    {
      "word": "почув",
      "exercise_type": "fill-in",
      "context": "Я почув гучний _____ на вулиці."
    },
    {
      "word": "вулиці",
      "exercise_type": "fill-in",
      "context": "Я почув гучний _____ на вулиці."
    },
    {
      "word": "кричання",
      "exercise_type": "fill-in",
      "context": "кричання"
    },
    {
      "word": "наступний",
      "exercise_type": "fill-in",
      "context": "Твій наступний _____ у цій грі."
    },
    {
      "word": "грі",
      "exercise_type": "fill-in",
      "context": "Твій наступний _____ у цій грі."
    },
    {
      "word": "домом",
      "exercise_type": "quiz",
      "context": "домом"
    },
    {
      "word": "домові",
      "exercise_type": "quiz",
      "context": "домові"
    },
    {
      "word": "проблем",
      "exercise_type": "quiz",
      "context": "проблем"
    },
    {
      "word": "проблемою",
      "exercise_type": "quiz",
      "context": "проблемою"
    },
    {
      "word": "фактам",
      "exercise_type": "quiz",
      "context": "фактам"
    },
    {
      "word": "фактами",
      "exercise_type": "quiz",
      "context": "фактами"
    },
    {
      "word": "мов",
      "exercise_type": "quiz",
      "context": "мов"
    },
    {
      "word": "листом",
      "exercise_type": "quiz",
      "context": "листом"
    },
    {
      "word": "листу",
      "exercise_type": "quiz",
      "context": "листу"
    },
    {
      "word": "книгу",
      "exercise_type": "quiz",
      "context": "читати книгу -> читання..."
    },
    {
      "word": "книги",
      "exercise_type": "quiz",
      "context": "книги"
    },
    {
      "word": "книг",
      "exercise_type": "quiz",
      "context": "книг"
    },
    {
      "word": "книгою",
      "exercise_type": "quiz",
      "context": "книгою"
    },
    {
      "word": "емоційним",
      "exercise_type": "true-false",
      "context": "Номіналізація робить текст більш емоційним і суб'єктивним."
    },
    {
      "word": "суб'єктивним",
      "exercise_type": "true-false",
      "context": "Номіналізація робить текст більш емоційним і суб'єктивним."
    },
    {
      "word": "написаний",
      "exercise_type": "true-false",
      "context": "Текст 1 написаний в інформаційному, офіційному стилі."
    },
    {
      "word": "ритмічним",
      "exercise_type": "true-false",
      "context": "Безафіксні іменники роблять текст більш ритмічним та лаконіч"
    },
    {
      "word": "лаконічним",
      "exercise_type": "true-false",
      "context": "Безафіксні іменники роблять текст більш ритмічним та лаконіч"
    },
    {
      "word": "втратило",
      "exercise_type": "true-false",
      "context": "Слово «будівництво» повністю втратило будь-який зв'язок з ді"
    },
    {
      "word": "зв'язок",
      "exercise_type": "true-false",
      "context": "Слово «будівництво» повністю втратило будь-який зв'язок з ді"
    },
    {
      "word": "готуючи",
      "exercise_type": "fill-in",
      "context": "Готуючи"
    },
    {
      "word": "підписав",
      "exercise_type": "fill-in",
      "context": "Він підписав офіційне _____ до Президента."
    },
    {
      "word": "звертання",
      "exercise_type": "fill-in",
      "context": "звертання"
    },
    {
      "word": "захищення",
      "exercise_type": "fill-in",
      "context": "захищення"
    },
    {
      "word": "мій",
      "exercise_type": "fill-in",
      "context": "Мій телефон вимагає системне _____."
    },
    {
      "word": "восени",
      "exercise_type": "fill-in",
      "context": "Восени ми спостерігали _____ листя."
    },
    {
      "word": "спостерігали",
      "exercise_type": "fill-in",
      "context": "Восени ми спостерігали _____ листя."
    },
    {
      "word": "падання",
      "exercise_type": "fill-in",
      "context": "падання"
    },
    {
      "word": "тієї",
      "exercise_type": "fill-in",
      "context": "Після тієї події старі традиції пішли в повне _____."
    },
    {
      "word": "події",
      "exercise_type": "fill-in",
      "context": "Після тієї події старі традиції пішли в повне _____."
    },
    {
      "word": "старі",
      "exercise_type": "fill-in",
      "context": "Після тієї події старі традиції пішли в повне _____."
    },
    {
      "word": "пішли",
      "exercise_type": "fill-in",
      "context": "Після тієї події старі традиції пішли в повне _____."
    },
    {
      "word": "забування",
      "exercise_type": "fill-in",
      "context": "забування"
    },
    {
      "word": "корисне",
      "exercise_type": "fill-in",
      "context": "Спортивне _____ дуже корисне для здоров'я."
    },
    {
      "word": "вчора",
      "exercise_type": "fill-in",
      "context": "Вчора почалося _____ нового проєкту."
    },
    {
      "word": "почалося",
      "exercise_type": "fill-in",
      "context": "Вчора почалося _____ нового проєкту."
    },
    {
      "word": "знати",
      "exercise_type": "match-up",
      "context": "знати"
    },
    {
      "word": "довгих",
      "exercise_type": "error-correction",
      "context": "Будівництво новий дім тривало два довгих роки."
    },
    {
      "word": "роки",
      "exercise_type": "error-correction",
      "context": "Будівництво новий дім тривало два довгих роки."
    },
    {
      "word": "новому",
      "exercise_type": "error-correction",
      "context": "новому дому"
    },
    {
      "word": "мене",
      "exercise_type": "error-correction",
      "context": "Написання довгий лист забрало у мене весь вчорашній вечір."
    },
    {
      "word": "вчорашній",
      "exercise_type": "error-correction",
      "context": "Написання довгий лист забрало у мене весь вчорашній вечір."
    },
    {
      "word": "вечір",
      "exercise_type": "error-correction",
      "context": "Написання довгий лист забрало у мене весь вчорашній вечір."
    },
    {
      "word": "довгому",
      "exercise_type": "error-correction",
      "context": "довгому листу"
    },
    {
      "word": "обкладинка",
      "exercise_type": "error-correction",
      "context": "Створення ця обкладинка — наш головний пріоритет на сьогодні"
    },
    {
      "word": "обкладинку",
      "exercise_type": "error-correction",
      "context": "цю обкладинку"
    },
    {
      "word": "обкладинці",
      "exercise_type": "error-correction",
      "context": "цій обкладинці"
    },
    {
      "word": "вранці",
      "exercise_type": "error-correction",
      "context": "Обговорення новий проєкт відбудеться завтра вранці."
    },
    {
      "word": "проєктом",
      "exercise_type": "error-correction",
      "context": "новим проєктом"
    },
    {
      "word": "найкраще",
      "exercise_type": "quiz",
      "context": "Який варіант найкраще підходить для офіційного документа чи "
    },
    {
      "word": "документа",
      "exercise_type": "quiz",
      "context": "Який варіант найкраще підходить для офіційного документа чи "
    },
    {
      "word": "наукової",
      "exercise_type": "quiz",
      "context": "Який варіант найкраще підходить для офіційного документа чи "
    },
    {
      "word": "досліджування",
      "exercise_type": "quiz",
      "context": "Наше довге досліджування проблеми дало нові знання."
    },
    {
      "word": "дослідили",
      "exercise_type": "quiz",
      "context": "Ми зібралися і дослідили проблему повністю."
    },
    {
      "word": "важкої",
      "exercise_type": "quiz",
      "context": "Яке речення є прикладом важкої стилістичної помилки, яку наз"
    },
    {
      "word": "стилістичної",
      "exercise_type": "quiz",
      "context": "Яке речення є прикладом важкої стилістичної помилки, яку наз"
    },
    {
      "word": "помилки",
      "exercise_type": "quiz",
      "context": "Яке речення є прикладом важкої стилістичної помилки, яку наз"
    },
    {
      "word": "розпочнеться",
      "exercise_type": "quiz",
      "context": "Обговорення проєкту розпочнеться завтра вранці."
    },
    {
      "word": "неформальне",
      "exercise_type": "quiz",
      "context": "Ви пишете неформальне повідомлення другу про свої ранкові тр"
    },
    {
      "word": "повідомлення",
      "exercise_type": "quiz",
      "context": "Ви пишете неформальне повідомлення другу про свої ранкові тр"
    },
    {
      "word": "другу",
      "exercise_type": "quiz",
      "context": "Ви пишете неформальне повідомлення другу про свої ранкові тр"
    },
    {
      "word": "ранкові",
      "exercise_type": "quiz",
      "context": "Ви пишете неформальне повідомлення другу про свої ранкові тр"
    },
    {
      "word": "тренування",
      "exercise_type": "quiz",
      "context": "Ви пишете неформальне повідомлення другу про свої ранкові тр"
    },
    {
      "word": "оберете",
      "exercise_type": "quiz",
      "context": "Ви пишете неформальне повідомлення другу про свої ранкові тр"
    },
    {
      "word": "перебігання",
      "exercise_type": "quiz",
      "context": "перебігання"
    },
    {
      "word": "пробігання",
      "exercise_type": "quiz",
      "context": "пробігання"
    },
    {
      "word": "нейтральним",
      "exercise_type": "quiz",
      "context": "Слово «розмова» є стилістично нейтральним. А яке слово з так"
    },
    {
      "word": "таким",
      "exercise_type": "quiz",
      "context": "Слово «розмова» є стилістично нейтральним. А яке слово з так"
    },
    {
      "word": "значенням",
      "exercise_type": "quiz",
      "context": "Слово «розмова» є стилістично нейтральним. А яке слово з так"
    },
    {
      "word": "професійно",
      "exercise_type": "quiz",
      "context": "Слово «розмова» є стилістично нейтральним. А яке слово з так"
    },
    {
      "word": "балаканина",
      "exercise_type": "quiz",
      "context": "балаканина"
    },
    {
      "word": "розмовляння",
      "exercise_type": "quiz",
      "context": "розмовляння"
    },
    {
      "word": "найпростіше",
      "exercise_type": "quiz",
      "context": "Як найкраще і найпростіше виправити канцелярську фразу «Дире"
    },
    {
      "word": "канцелярську",
      "exercise_type": "quiz",
      "context": "Як найкраще і найпростіше виправити канцелярську фразу «Дире"
    },
    {
      "word": "виконалося",
      "exercise_type": "quiz",
      "context": "Дирекцією виконалося рішення про продажі."
    },
    {
      "word": "продажі",
      "exercise_type": "quiz",
      "context": "Дирекцією виконалося рішення про продажі."
    },
    {
      "word": "прийняла",
      "exercise_type": "quiz",
      "context": "Дирекція прийняла рішення про процес виконання."
    },
    {
      "word": "вирішено",
      "exercise_type": "quiz",
      "context": "Виконання плану було вирішено дирекцією."
    },
    {
      "word": "живо",
      "exercise_type": "quiz",
      "context": "Який варіант звучить найбільш природно та живо для щоденної "
    },
    {
      "word": "щоденної",
      "exercise_type": "quiz",
      "context": "Який варіант звучить найбільш природно та живо для щоденної "
    },
    {
      "word": "бесіди",
      "exercise_type": "quiz",
      "context": "Який варіант звучить найбільш природно та живо для щоденної "
    },
    {
      "word": "шукав",
      "exercise_type": "quiz",
      "context": "Я дуже довго шукав ключі в кімнаті."
    },
    {
      "word": "ключі",
      "exercise_type": "quiz",
      "context": "Я дуже довго шукав ключі в кімнаті."
    },
    {
      "word": "кімнаті",
      "exercise_type": "quiz",
      "context": "Я дуже довго шукав ключі в кімнаті."
    },
    {
      "word": "пошуку",
      "exercise_type": "quiz",
      "context": "Процес пошуку ключів зайняв багато часу."
    },
    {
      "word": "тривалим",
      "exercise_type": "quiz",
      "context": "Шукання ключів у кімнаті було тривалим."
    },
    {
      "word": "доповіді",
      "exercise_type": "quiz",
      "context": "У науковій доповіді про властивості металів доречно і профес"
    },
    {
      "word": "властивості",
      "exercise_type": "quiz",
      "context": "У науковій доповіді про властивості металів доречно і профес"
    },
    {
      "word": "доречно",
      "exercise_type": "quiz",
      "context": "У науковій доповіді про властивості металів доречно і профес"
    },
    {
      "word": "іде",
      "exercise_type": "quiz",
      "context": "Вивчання нових металів іде добре."
    },
    {
      "word": "вивчали",
      "exercise_type": "quiz",
      "context": "Ми довго вивчали нові метали і нарешті завершили."
    },
    {
      "word": "метали",
      "exercise_type": "quiz",
      "context": "Ми довго вивчали нові метали і нарешті завершили."
    },
    {
      "word": "нарешті",
      "exercise_type": "quiz",
      "context": "Ми довго вивчали нові метали і нарешті завершили."
    },
    {
      "word": "завершили",
      "exercise_type": "quiz",
      "context": "Ми довго вивчали нові метали і нарешті завершили."
    },
    {
      "word": "закінчено",
      "exercise_type": "quiz",
      "context": "Процес вивчання металів було закінчено."
    },
    {
      "word": "виберіть",
      "exercise_type": "quiz",
      "context": "Виберіть речення, у якому немає стилістичних помилок (канцел"
    },
    {
      "word": "стилістичних",
      "exercise_type": "quiz",
      "context": "Виберіть речення, у якому немає стилістичних помилок (канцел"
    },
    {
      "word": "здійснено",
      "exercise_type": "quiz",
      "context": "Було здійснено забезпечення швидкого відновлення інфраструкт"
    },
    {
      "word": "швидкого",
      "exercise_type": "quiz",
      "context": "Було здійснено забезпечення швидкого відновлення інфраструкт"
    },
    {
      "word": "зробили",
      "exercise_type": "quiz",
      "context": "Ми зробили кроки для процесу відновлення інфраструктури."
    },
    {
      "word": "зроблене",
      "exercise_type": "quiz",
      "context": "Відновлення інфраструктури було зроблене нами швидко."
    },
    {
      "word": "швидко",
      "exercise_type": "quiz",
      "context": "Відновлення інфраструктури було зроблене нами швидко."
    },
    {
      "word": "відновили",
      "exercise_type": "quiz",
      "context": "Ми швидко відновили зруйновану інфраструктуру."
    },
    {
      "word": "зруйновану",
      "exercise_type": "quiz",
      "context": "Ми швидко відновили зруйновану інфраструктуру."
    },
    {
      "word": "інфраструктуру",
      "exercise_type": "quiz",
      "context": "Ми швидко відновили зруйновану інфраструктуру."
    }
  ],
  "vocab_coverage": {
    "plan_vocab_total": 26,
    "tested_in_exercises": 20,
    "not_tested": [
      "виробництво",
      "основа",
      "приїзд",
      "продуктивний",
      "становлення",
      "інфінітива"
    ]
  },
  "all_grounded": false
}