{
  "mode": "v6",
  "track": "a2",
  "slug": "checkpoint-cases",
  "phases": {
    "check": {
      "status": "complete",
      "ts": "2026-04-12T19:21:41.430055+00:00"
    },
    "research": {
      "status": "complete",
      "ts": "2026-04-12T19:21:41.435848+00:00"
    },
    "skeleton": {
      "status": "complete",
      "ts": "2026-04-12T19:23:56.696342+00:00"
    },
    "pre-verify": {
      "status": "complete",
      "ts": "2026-04-12T19:26:41.770226+00:00"
    },
    "write": {
      "status": "complete",
      "ts": "2026-04-12T19:28:36.687525+00:00"
    },
    "exercises": {
      "status": "complete",
      "ts": "2026-04-12T19:28:36.687682+00:00"
    },
    "activities": {
      "status": "complete",
      "ts": "2026-04-12T19:33:07.791177+00:00"
    },
    "repair": {
      "status": "complete",
      "ts": "2026-04-12T19:33:07.831870+00:00"
    },
    "verify-exercises": {
      "status": "complete",
      "ts": "2026-04-12T19:33:07.910117+00:00"
    },
    "annotate": {
      "status": "complete",
      "ts": "2026-04-12T19:33:07.915569+00:00"
    },
    "vocab": {
      "status": "complete",
      "ts": "2026-04-12T19:33:52.420127+00:00"
    },
    "enrich": {
      "status": "complete",
      "ts": "2026-04-12T19:33:52.420289+00:00"
    },
    "verify": {
      "status": "complete",
      "ts": "2026-04-12T19:33:52.606262+00:00"
    },
    "review": {
      "status": "complete",
      "ts": "2026-04-12T19:45:18.496756+00:00"
    },
    "stress": {
      "status": "complete",
      "ts": "2026-04-12T19:45:18.644639+00:00"
    }
  }
}