{
  "$schema": "../../../schemas/vibe-module.schema.json",
  "lesson": {
    "id": "lesson-uk-A1-25",
    "moduleId": "mod-uk-A1-25",
    "languagePair": "l2-uk-en",
    "subject": "language",
    "owner": "curricula-opus",
    "visibility": "public",
    "language": "uk",
    "targetLevel": "A1",
    "phase": "A1.3",
    "moduleNumber": 25,
    "moduleType": "vocabulary",
    "immersionLevel": 0.3,
    "title": "Daily Routine",
    "subtitle": "A Day in Your Life",
    "description": "Describe your daily routine",
    "objectives": [
      "Describe your daily routine",
      "Use reflexive verbs for daily activities",
      "Sequence actions with time expressions",
      "Talk about habits and schedules"
    ],
    "grammarFocus": [
      "Reflexive verbs (-ся)",
      "Time expressions with о + locative",
      "Sequence words (потім, після того)"
    ],
    "tags": [
      "vocabulary",
      "practical",
      "verbs",
      "reflexive"
    ],
    "totalDuration": 50,
    "transliterationMode": "full",
    "sections": [
      {
        "id": "section-intro",
        "name": "Вступ",
        "nameEn": "Introduction",
        "type": "intro",
        "content": "## warm-up\n\n### What's Your Routine?\n\nEvery day we follow patterns: wake up, eat, work, sleep. Let's learn to describe YOUR typical day in Ukrainian!\n\nMany daily activities use **reflexive verbs** (-ся ending):\n- прокидатися (to wake up)\n- вмиватися (to wash oneself)\n- одягатися (to dress oneself)\n\n> 💡 **Did You Know?**\n>\n> Ukrainian reflexive verbs end in -ся (short for \"себе\" = oneself). This suffix stuck to the verb over centuries. Originally, \"я мию себе\" (I wash myself) became \"я миюся.\" Many everyday actions are reflexive - you do them TO yourself!\n\n## presentation\n\n### Morning Routine\n\n| Ukrainian | Transliteration | English |\n|-----------|-----------------|---------|\n| прокидатися | prokydatysya | to wake up |\n| вставати | vstavaty | to get up |\n| вмиватися | vmyvatysya | to wash (oneself) |\n| чистити зуби | chystyty zuby | to brush teeth |\n| голитися | holytysya | to shave |\n| одягатися | odyahatysya | to get dressed |\n| снідати | snidaty | to have breakfast |\n| пити каву | pyty kavu | to drink coffee |\n\n**Sample morning:**\n- Я **прокидаюся** о сьомій годині.\n- Потім я **встаю** і **вмиваюся**.\n- Я **чищу зуби** і **одягаюся**.\n- О пів на восьму я **снідаю**.\n\n> ⚡ **Pro Tip: Reflexive Conjugation**\n>\n> Reflexive verbs conjugate normally, but keep -ся:\n> - я вмиваюся\n> - ти вмиваєшся\n> - він вмивається\n> - ми вмиваємося\n> - ви вмиваєтеся\n> - вони вмиваються\n>\n> Note: -ся after vowels, -сь after consonants (informal)\n\n### Daytime Activities\n\n| Ukrainian | Transliteration | English |\n|-----------|-----------------|---------|\n| виходити з дому | vykhodity z domu | to leave home |\n| їхати на роботу | yikhaty na robotu | to go to work |\n| працювати | pratsyuvaty | to work |\n| обідати | obidaty | to have lunch |\n| повертатися | povertatysya | to return |\n| відпочивати | vidpochyvaty | to rest |\n\n**Sample day:**\n- О восьмій я **виходжу з дому**.\n- Я **їду на роботу** метро.\n- Я **працюю** з дев'ятої до шостої.\n- О першій я **обідаю**.\n- О сьомій я **повертаюся** додому.\n\n> 📜 **History Bite: Reflexive Evolution**\n>\n> The reflexive -ся comes from the pronoun \"себе\" (self). In Old East Slavic, verbs with \"ся\" were written separately: \"мыти ся.\" Over time, the pronoun merged with the verb. This happened across all Slavic languages - compare Russian \"-ся,\" Polish \"-się,\" Czech \"-se.\"\n\n### Evening Routine\n\n| Ukrainian | Transliteration | English |\n|-----------|-----------------|---------|\n| вечеряти | vecheryaty | to have dinner |\n| дивитися телевізор | dyvytysya televizor | to watch TV |\n| читати | chytaty | to read |\n| гуляти | hulyaty | to walk, stroll |\n| приймати душ | pryimaty dush | to take a shower |\n| роздягатися | rozdyahatysya | to undress |\n| лягати спати | lyahaty spaty | to go to bed |\n| засинати | zasynaty | to fall asleep |\n\n**Sample evening:**\n- О сьомій я **вечеряю** з родиною.\n- Потім я **дивлюся телевізор** або **читаю**.\n- О десятій я **приймаю душ**.\n- О одинадцятій я **лягаю спати**.\n- Я зазвичай **засинаю** швидко.\n\n> 🎯 **Fun Fact: Гуляти**\n>\n> \"Гуляти\" means both \"to walk/stroll\" AND \"to have fun/party\"! Context matters:\n> - Ми гуляємо в парку. (We're walking in the park.)\n> - Ми гуляємо на весіллі. (We're partying at a wedding.)\n>\n> Evening \"гуляння\" can mean a romantic evening stroll or a big party!\n\n### Time Expressions\n\n| Ukrainian | English |\n|-----------|---------|\n| о + locative | at (time) |\n| з... до... | from... to... |\n| вранці | in the morning |\n| вдень | during the day |\n| ввечері | in the evening |\n| вночі | at night |\n| щодня | every day |\n| зазвичай | usually |\n| завжди | always |\n| іноді | sometimes |\n| ніколи | never |\n\n> 🔗 **Language Link: Time Prepositions**\n>\n> - **О** сьомій = at 7 (specific time)\n> - **З** дев'ятої **до** шостої = from 9 to 6 (range)\n> - **Близько** восьмої = around 8 (approximate)\n>\n> All use locative case for hours!\n\n### Sequence Words\n\n| Ukrainian | English |\n|-----------|---------|\n| спочатку | first, at first |\n| потім | then, after that |\n| після того | after that |\n| нарешті | finally |\n| перед тим | before that |\n| одночасно | at the same time |\n\n**Using sequences:**\n- **Спочатку** я вмиваюся, **потім** снідаю.\n- **Перед тим**, як лягти спати, я читаю.\n- **Нарешті** я засинаю.\n\n> 🌍 **Real World: Describing Your Day**\n>\n> - **Як проходить твій день?** - How does your day go?\n> - **Що ти робиш вранці?** - What do you do in the morning?\n> - **О котрій ти встаєш?** - What time do you get up?\n> - **Коли ти лягаєш спати?** - When do you go to bed?\n\n## practice\n\n### Describe Routine Actions\n\nSay in Ukrainian:\n1. I wake up at 7.\n   > [!answer] Я прокидаюся о сьомій.\n2. She has breakfast at 8.\n   > [!answer] Вона снідає о восьмій.\n3. We work from 9 to 5.\n   > [!answer] Ми працюємо з дев'ятої до п'ятої.\n4. They go to bed at 11.\n   > [!answer] Вони лягають спати о одинадцятій.\n\n### Put in Order\n\nArrange these activities chronologically:\n- вечеряти → снідати → обідати\n\nAnswer: снідати, обідати, вечеряти\n\n### Complete the Routine\n\nFill in with reflexive verbs:\n1. Вранці я ___ (wake up).\n   > [!answer] прокидаюся\n2. Потім я ___ (wash).\n   > [!answer] вмиваюся\n3. Я ___ (get dressed).\n   > [!answer] одягаюся\n4. Ввечері я ___ (undress).\n   > [!answer] роздягаюся\n\n## production\n\n### Describe Your Day\n\nWrite or speak about your typical day:\n- О котрій ви прокидаєтеся?\n- Що ви робите вранці?\n- Коли ви працюєте/навчаєтеся?\n- Що ви робите ввечері?\n- О котрій ви лягаєте спати?\n\n---\n\n---\n\n---\n\n---\n\n---\n\n\n---\n\n\n---"
      },
      {
        "id": "section-daily-routine-summary",
        "name": "Daily Routine Summary",
        "type": "content",
        "content": "## Reflexive Verbs (-ся)\n\n| Verb | I | You | He/She |\n|------|---|-----|--------|\n| прокидатися | прокидаюся | прокидаєшся | прокидається |\n| вмиватися | вмиваюся | вмиваєшся | вмивається |\n| одягатися | одягаюся | одягаєшся | одягається |\n\n## Time Expressions\n\n| Expression | Example |\n|------------|---------|\n| о + Loc. | о сьомій (at 7) |\n| з ... до | з 9 до 5 |\n| вранці | вранці я снідаю |\n| ввечері | ввечері я відпочиваю |\n| щодня | я щодня працюю |\n\n---"
      },
      {
        "id": "section-summary",
        "name": "Підсумок",
        "nameEn": "Summary",
        "type": "summary",
        "content": "> 💡 **What You Learned Today**\n>\n> - Reflexive verbs: прокидатися, вмиватися, одягатися\n> - Meal verbs: снідати, обідати, вечеряти\n> - Sequence words: спочатку, потім, нарешті\n> - Frequency: щодня, зазвичай, завжди, іноді\n> - Time expressions: о сьомій, з... до..., вранці/ввечері\n\n> 🎯 **Coming Next**\n>\n> In Module 26, you'll learn **adjectives**:\n> - Великий дім, велика кімната, велике вікно\n> - Agreement with gender\n> - Common descriptive adjectives"
      }
    ],
    "rawMarkdown": "---\nmodule: 25\ntitle: \"Daily Routine\"\nsubtitle: \"A Day in Your Life\"\nlevel: A1\nphase: A1.3\nduration: 50\ntransliteration: full\ntags: [vocabulary, practical, verbs, reflexive]\nobjectives:\n  - Describe your daily routine\n  - Use reflexive verbs for daily activities\n  - Sequence actions with time expressions\n  - Talk about habits and schedules\ngrammar:\n  - Reflexive verbs (-ся)\n  - Time expressions with о + locative\n  - Sequence words (потім, після того)\n---\n\n# Lesson Content\n\n## warm-up\n\n### What's Your Routine?\n\nEvery day we follow patterns: wake up, eat, work, sleep. Let's learn to describe YOUR typical day in Ukrainian!\n\nMany daily activities use **reflexive verbs** (-ся ending):\n- прокидатися (to wake up)\n- вмиватися (to wash oneself)\n- одягатися (to dress oneself)\n\n> 💡 **Did You Know?**\n>\n> Ukrainian reflexive verbs end in -ся (short for \"себе\" = oneself). This suffix stuck to the verb over centuries. Originally, \"я мию себе\" (I wash myself) became \"я миюся.\" Many everyday actions are reflexive - you do them TO yourself!\n\n## presentation\n\n### Morning Routine\n\n| Ukrainian | Transliteration | English |\n|-----------|-----------------|---------|\n| прокидатися | prokydatysya | to wake up |\n| вставати | vstavaty | to get up |\n| вмиватися | vmyvatysya | to wash (oneself) |\n| чистити зуби | chystyty zuby | to brush teeth |\n| голитися | holytysya | to shave |\n| одягатися | odyahatysya | to get dressed |\n| снідати | snidaty | to have breakfast |\n| пити каву | pyty kavu | to drink coffee |\n\n**Sample morning:**\n- Я **прокидаюся** о сьомій годині.\n- Потім я **встаю** і **вмиваюся**.\n- Я **чищу зуби** і **одягаюся**.\n- О пів на восьму я **снідаю**.\n\n> ⚡ **Pro Tip: Reflexive Conjugation**\n>\n> Reflexive verbs conjugate normally, but keep -ся:\n> - я вмиваюся\n> - ти вмиваєшся\n> - він вмивається\n> - ми вмиваємося\n> - ви вмиваєтеся\n> - вони вмиваються\n>\n> Note: -ся after vowels, -сь after consonants (informal)\n\n### Daytime Activities\n\n| Ukrainian | Transliteration | English |\n|-----------|-----------------|---------|\n| виходити з дому | vykhodity z domu | to leave home |\n| їхати на роботу | yikhaty na robotu | to go to work |\n| працювати | pratsyuvaty | to work |\n| обідати | obidaty | to have lunch |\n| повертатися | povertatysya | to return |\n| відпочивати | vidpochyvaty | to rest |\n\n**Sample day:**\n- О восьмій я **виходжу з дому**.\n- Я **їду на роботу** метро.\n- Я **працюю** з дев'ятої до шостої.\n- О першій я **обідаю**.\n- О сьомій я **повертаюся** додому.\n\n> 📜 **History Bite: Reflexive Evolution**\n>\n> The reflexive -ся comes from the pronoun \"себе\" (self). In Old East Slavic, verbs with \"ся\" were written separately: \"мыти ся.\" Over time, the pronoun merged with the verb. This happened across all Slavic languages - compare Russian \"-ся,\" Polish \"-się,\" Czech \"-se.\"\n\n### Evening Routine\n\n| Ukrainian | Transliteration | English |\n|-----------|-----------------|---------|\n| вечеряти | vecheryaty | to have dinner |\n| дивитися телевізор | dyvytysya televizor | to watch TV |\n| читати | chytaty | to read |\n| гуляти | hulyaty | to walk, stroll |\n| приймати душ | pryimaty dush | to take a shower |\n| роздягатися | rozdyahatysya | to undress |\n| лягати спати | lyahaty spaty | to go to bed |\n| засинати | zasynaty | to fall asleep |\n\n**Sample evening:**\n- О сьомій я **вечеряю** з родиною.\n- Потім я **дивлюся телевізор** або **читаю**.\n- О десятій я **приймаю душ**.\n- О одинадцятій я **лягаю спати**.\n- Я зазвичай **засинаю** швидко.\n\n> 🎯 **Fun Fact: Гуляти**\n>\n> \"Гуляти\" means both \"to walk/stroll\" AND \"to have fun/party\"! Context matters:\n> - Ми гуляємо в парку. (We're walking in the park.)\n> - Ми гуляємо на весіллі. (We're partying at a wedding.)\n>\n> Evening \"гуляння\" can mean a romantic evening stroll or a big party!\n\n### Time Expressions\n\n| Ukrainian | English |\n|-----------|---------|\n| о + locative | at (time) |\n| з... до... | from... to... |\n| вранці | in the morning |\n| вдень | during the day |\n| ввечері | in the evening |\n| вночі | at night |\n| щодня | every day |\n| зазвичай | usually |\n| завжди | always |\n| іноді | sometimes |\n| ніколи | never |\n\n> 🔗 **Language Link: Time Prepositions**\n>\n> - **О** сьомій = at 7 (specific time)\n> - **З** дев'ятої **до** шостої = from 9 to 6 (range)\n> - **Близько** восьмої = around 8 (approximate)\n>\n> All use locative case for hours!\n\n### Sequence Words\n\n| Ukrainian | English |\n|-----------|---------|\n| спочатку | first, at first |\n| потім | then, after that |\n| після того | after that |\n| нарешті | finally |\n| перед тим | before that |\n| одночасно | at the same time |\n\n**Using sequences:**\n- **Спочатку** я вмиваюся, **потім** снідаю.\n- **Перед тим**, як лягти спати, я читаю.\n- **Нарешті** я засинаю.\n\n> 🌍 **Real World: Describing Your Day**\n>\n> - **Як проходить твій день?** - How does your day go?\n> - **Що ти робиш вранці?** - What do you do in the morning?\n> - **О котрій ти встаєш?** - What time do you get up?\n> - **Коли ти лягаєш спати?** - When do you go to bed?\n\n## practice\n\n### Describe Routine Actions\n\nSay in Ukrainian:\n1. I wake up at 7.\n   > [!answer] Я прокидаюся о сьомій.\n2. She has breakfast at 8.\n   > [!answer] Вона снідає о восьмій.\n3. We work from 9 to 5.\n   > [!answer] Ми працюємо з дев'ятої до п'ятої.\n4. They go to bed at 11.\n   > [!answer] Вони лягають спати о одинадцятій.\n\n### Put in Order\n\nArrange these activities chronologically:\n- вечеряти → снідати → обідати\n\nAnswer: снідати, обідати, вечеряти\n\n### Complete the Routine\n\nFill in with reflexive verbs:\n1. Вранці я ___ (wake up).\n   > [!answer] прокидаюся\n2. Потім я ___ (wash).\n   > [!answer] вмиваюся\n3. Я ___ (get dressed).\n   > [!answer] одягаюся\n4. Ввечері я ___ (undress).\n   > [!answer] роздягаюся\n\n## production\n\n### Describe Your Day\n\nWrite or speak about your typical day:\n- О котрій ви прокидаєтеся?\n- Що ви робите вранці?\n- Коли ви працюєте/навчаєтеся?\n- Що ви робите ввечері?\n- О котрій ви лягаєте спати?\n\n---\n\n---\n\n---\n\n---\n\n---\n\n# Activities\n\n## fill-in: Daily Routine Verbs\n\n> Choose the correct reflexive verb form.\n\n1. Я зазвичай ___ о сьомій годині кожен ранок. (to wake up)\n   > [!answer] прокидаюся\n   > [!options] прокидаюся | прокидаєшся | прокидається | прокидаються\n\n2. Потім я швидко ___ і чищу зуби у ванній. (to wash - reflexive)\n   > [!answer] вмиваюся\n   > [!options] вмиваюся | вмиваєшся | вмивається | вмиваються\n\n3. Вона завжди ___ дуже швидко вранці перед роботою. (to get dressed)\n   > [!answer] одягається\n   > [!options] одягаюся | одягаєшся | одягається | одягаються\n\n4. О восьмій годині я зазвичай ___ на кухні. (to have breakfast)\n   > [!answer] снідаю\n   > [!options] снідаю | снідаєш | снідає | снідають\n\n5. Він щодня ___ з роботи о шостій годині ввечері. (to return)\n   > [!answer] повертається\n   > [!options] повертаюся | повертаєшся | повертається | повертаються\n\n6. Ввечері ми завжди разом ___ вдома всією родиною. (to have dinner)\n   > [!answer] вечеряємо\n   > [!options] вечеряю | вечеряєш | вечеряє | вечеряємо\n\n7. Вони зазвичай ___ спати о одинадцятій годині ввечері. (to go to bed)\n   > [!answer] лягають\n   > [!options] лягаю | лягаєш | лягає | лягають\n\n8. Я завжди ___ зуби двічі на день: вранці і ввечері. (to brush)\n   > [!answer] чищу\n   > [!options] чищу | чистиш | чистить | чистять\n\n9. Він щоранку ___ у ванній перед сніданком. (to shave)\n   > [!answer] голиться\n   > [!options] голюся | голишся | голиться | голяться\n\n10. Вона завжди дуже швидко ___ після важкого дня. (to fall asleep)\n   > [!answer] засинає\n   > [!options] засинаю | засинаєш | засинає | засинають\n\n## unjumble: Build the Sentence\n\n> Arrange the words in the correct order.\n\n1. прокидаюся / о / Я / сьомій / зазвичай / годині / кожен / ранок\n   > [!answer] Я зазвичай прокидаюся о сьомій годині кожен ранок.\n   > (I usually wake up at 7 o'clock every morning.) [8 words]\n\n2. вмивається / Він / потім / швидко / у / ванній / і / одягається\n   > [!answer] Потім він швидко вмивається у ванній і одягається.\n   > (Then he quickly washes up in the bathroom and gets dressed.) [8 words]\n\n3. снідає / восьмій / Вона / о / завжди / на / кухні / годині\n   > [!answer] Вона завжди снідає о восьмій годині на кухні.\n   > (She always has breakfast at 8 o'clock in the kitchen.) [8 words]\n\n4. з / до / працюю / дев'ятої / п'ятої / Я / щодня / офісі / у\n   > [!answer] Я щодня працюю у офісі з дев'ятої до п'ятої.\n   > (I work at the office every day from 9 to 5.) [9 words]\n\n5. повертаємося / додому / Ми / ввечері / пізно / дуже / з / роботи\n   > [!answer] Ми повертаємося з роботи додому дуже пізно ввечері.\n   > (We return home from work very late in the evening.) [8 words]\n\n6. лягають / Вони / спати / о / одинадцятій / зазвичай / годині / ввечері\n   > [!answer] Вони зазвичай лягають спати о одинадцятій годині ввечері.\n   > (They usually go to bed at 11 PM.) [8 words]\n\n7. вранці / чищу / Я / зуби / завжди / і / ввечері / двічі\n   > [!answer] Я завжди чищу зуби двічі: вранці і ввечері.\n   > (I always brush my teeth twice: in the morning and evening.) [8 words]\n\n8. одягаюся / Спочатку / я / потім / снідаю / швидко / на / кухні\n   > [!answer] Спочатку я швидко одягаюся, потім снідаю на кухні.\n   > (First I quickly get dressed, then I have breakfast in the kitchen.) [8 words]\n\n9. швидко / засинає / Він / зазвичай / ввечері / дуже / після / роботи\n   > [!answer] Він зазвичай дуже швидко засинає ввечері після роботи.\n   > (He usually falls asleep very quickly in the evening after work.) [8 words]\n\n10. щодня / снідаю / Я / о / восьмій / годині / кухні / на\n    > [!answer] Я щодня снідаю о восьмій годині на кухні.\n    > (I have breakfast every day at 8 o'clock in the kitchen.) [8 words]\n\n## match-up: Daily Routine Vocabulary\n\n> Match Ukrainian daily routine words to their English meanings.\n\n| Left | Right |\n|------|-------|\n| прокидатися | to wake up |\n| вставати | to get up |\n| вмиватися | to wash (face) |\n| одягатися | to get dressed |\n| снідати | to have breakfast |\n| обідати | to have lunch |\n| вечеряти | to have dinner |\n| повертатися | to return |\n| лягати спати | to go to bed |\n| засинати | to fall asleep |\n\n## quiz: Daily Routine Grammar\n\n> Choose the correct answer.\n\n1. What does -ся at the end of verbs indicate?\n   - [x] reflexive action (done to oneself)\n   - [ ] past tense\n   - [ ] future tense\n   - [ ] negative\n   > -ся means \"oneself\" (from себе)\n\n2. What is \"я прокидаюся\" in English?\n   - [x] I wake up\n   - [ ] I get dressed\n   - [ ] I wash\n   - [ ] I return\n   > прокидатися = to wake up\n\n3. How do you say \"at 7 o'clock\"?\n   - [x] о сьомій\n   - [ ] у сім\n   - [ ] на сьомій\n   - [ ] до сьомої\n   > о + ordinal number in locative\n\n4. What does \"щодня\" mean?\n   - [x] every day\n   - [ ] sometimes\n   - [ ] never\n   - [ ] always\n   > щодня = every day\n\n5. What is \"спочатку\" in English?\n   - [x] first, at first\n   - [ ] then\n   - [ ] finally\n   - [ ] later\n   > спочатку = first\n\n6. How do you say \"I brush my teeth\"?\n   - [x] Я чищу зуби\n   - [ ] Я вмиваю зуби\n   - [ ] Я голю зуби\n   - [ ] Я миваю зуби\n   > чистити зуби = to brush teeth\n\n7. What does \"зазвичай\" mean?\n   - [x] usually\n   - [ ] always\n   - [ ] never\n   - [ ] sometimes\n   > зазвичай = usually\n\n8. How do you say \"I work from 9 to 5\"?\n   - [x] Я працюю з дев'ятої до п'ятої\n   - [ ] Я працюю о дев'ятій о п'ятій\n   - [ ] Я працюю у дев'ять до п'ять\n   - [ ] Я працюю від 9 до 5\n   > з... до... + genitive of ordinal numbers\n\n9. What is \"лягати спати\"?\n   - [x] to go to bed\n   - [ ] to wake up\n   - [ ] to fall asleep\n   - [ ] to get up\n   > лягати спати = to lie down to sleep\n\n10. What does \"ввечері\" mean?\n   - [x] in the evening\n   - [ ] in the morning\n   - [ ] at night\n   - [ ] during the day\n   > ввечері = in the evening\n\n## true-false: True or False?\n\n> Determine if each statement is true or false.\n\n- [x] Reflexive verbs end in -ся\n   > Correct!\n\n- [x] \"Прокидатися\" means \"to wake up\"\n   > Correct!\n\n- [ ] \"Вставати\" and \"прокидатися\" mean the same thing\n   > Incorrect. вставати = to get up, прокидатися = to wake up\n\n- [x] \"Чистити зуби\" means \"to brush teeth\"\n   > Correct!\n\n- [x] \"Щодня\" means \"every day\"\n   > Correct!\n\n- [ ] \"Вмиватися\" means \"to shower\"\n   > Incorrect. вмиватися = to wash (face), приймати душ = to shower\n\n- [x] \"Спочатку\" means \"first\"\n   > Correct!\n\n- [x] \"Засинати\" means \"to fall asleep\"\n   > Correct!\n\n- [ ] \"Ввечері\" means \"in the morning\"\n   > Incorrect. ввечері = in the evening, вранці = in the morning\n\n- [x] Time expressions use \"о\" + locative case\n   > Correct!\n\n## group-sort: Daily Routine Categories\n\n> Sort these activities by time of day.\n\n### Morning Activities\n- прокидатися (wake up)\n- вмиватися (wash)\n- снідати (have breakfast)\n- одягатися (get dressed)\n\n### Daytime Activities\n- працювати (work)\n- обідати (have lunch)\n- виходити з дому (leave home)\n\n### Evening Activities\n- повертатися (return)\n- вечеряти (have dinner)\n- лягати спати (go to bed)\n- засинати (fall asleep)\n\n---\n\n# Vocabulary\n\n| Word | IPA | English | POS | Gender | Note |\n|------|-----|---------|-----|--------|------|\n| прокидатися | /prɔkɪˈdɑtɪsʲɑ/ | to wake up | verb | - | Reflexive |\n| вставати | /vstɑˈvɑtɪ/ | to get up | verb | - | встаю, встаєш |\n| вмиватися | /vmɪˈvɑtɪsʲɑ/ | to wash (face) | verb | - | Reflexive |\n| одягатися | /ɔˈdʲɑɦɑtɪsʲɑ/ | to get dressed | verb | - | Reflexive |\n| роздягатися | /rɔzˈdʲɑɦɑtɪsʲɑ/ | to undress | verb | - | Reflexive |\n| снідати | /snʲiˈdɑtɪ/ | to have breakfast | verb | - |\n| обідати | /ɔˈbʲidɑtɪ/ | to have lunch | verb | - |\n| вечеряти | /vɛtʃɛˈrʲɑtɪ/ | to have dinner | verb | - |\n| виходити | /vɪxɔˈdɪtɪ/ | to go out, leave | verb | - |\n| повертатися | /pɔvɛrˈtɑtɪsʲɑ/ | to return | verb | - | Reflexive |\n| лягати | /lʲɑˈɦɑtɪ/ | to lie down | verb | - | лягати спати |\n| засинати | /zɑsɪˈnɑtɪ/ | to fall asleep | verb | - |\n| голитися | /ɦɔˈlɪtɪsʲɑ/ | to shave | verb | - | Reflexive |\n| чистити | /ˈtʃɪstɪtɪ/ | to clean, brush | verb | - | чистити зуби |\n| душ | /duʃ/ | shower | noun | m | приймати душ |\n| зуби | /ˈzubɪ/ | teeth | noun | pl | Singular: зуб |\n| спочатку | /spɔˈtʃɑtku/ | first, at first | adv | - |\n| зазвичай | /zɑˈzvɪtʃɑj/ | usually | adv | - |\n| щодня | /ʃtʃɔˈdnʲɑ/ | every day | adv | - |\n\n---\n\n# Daily Routine Summary\n\n## Reflexive Verbs (-ся)\n\n| Verb | I | You | He/She |\n|------|---|-----|--------|\n| прокидатися | прокидаюся | прокидаєшся | прокидається |\n| вмиватися | вмиваюся | вмиваєшся | вмивається |\n| одягатися | одягаюся | одягаєшся | одягається |\n\n## Time Expressions\n\n| Expression | Example |\n|------------|---------|\n| о + Loc. | о сьомій (at 7) |\n| з ... до | з 9 до 5 |\n| вранці | вранці я снідаю |\n| ввечері | ввечері я відпочиваю |\n| щодня | я щодня працюю |\n\n---\n\n# Summary\n\n> 💡 **What You Learned Today**\n>\n> - Reflexive verbs: прокидатися, вмиватися, одягатися\n> - Meal verbs: снідати, обідати, вечеряти\n> - Sequence words: спочатку, потім, нарешті\n> - Frequency: щодня, зазвичай, завжди, іноді\n> - Time expressions: о сьомій, з... до..., вранці/ввечері\n\n> 🎯 **Coming Next**\n>\n> In Module 26, you'll learn **adjectives**:\n> - Великий дім, велика кімната, велике вікно\n> - Agreement with gender\n> - Common descriptive adjectives\n",
    "createdAt": "2025-12-03T08:52:31.861Z",
    "modifiedAt": "2025-12-03T08:52:31.861Z",
    "version": 2
  },
  "activities": [
    {
      "id": "act-a1-25-fillblank",
      "type": "fill-blank",
      "title": "Daily Routine Verbs",
      "description": "Choose the correct reflexive verb form.",
      "content": {
        "type": "fill-blank",
        "items": [
          {
            "prompt": "Я зазвичай ___ о сьомій годині кожен ранок. (to wake up)",
            "answer": "прокидаюся",
            "options": [
              "прокидаюся",
              "прокидаєшся",
              "прокидається",
              "прокидаються"
            ]
          },
          {
            "prompt": "Потім я швидко ___ і чищу зуби у ванній. (to wash - reflexive)",
            "answer": "вмиваюся",
            "options": [
              "вмиваюся",
              "вмиваєшся",
              "вмивається",
              "вмиваються"
            ]
          },
          {
            "prompt": "Вона завжди ___ дуже швидко вранці перед роботою. (to get dressed)",
            "answer": "одягається",
            "options": [
              "одягаюся",
              "одягаєшся",
              "одягається",
              "одягаються"
            ]
          },
          {
            "prompt": "О восьмій годині я зазвичай ___ на кухні. (to have breakfast)",
            "answer": "снідаю",
            "options": [
              "снідаю",
              "снідаєш",
              "снідає",
              "снідають"
            ]
          },
          {
            "prompt": "Він щодня ___ з роботи о шостій годині ввечері. (to return)",
            "answer": "повертається",
            "options": [
              "повертаюся",
              "повертаєшся",
              "повертається",
              "повертаються"
            ]
          },
          {
            "prompt": "Ввечері ми завжди разом ___ вдома всією родиною. (to have dinner)",
            "answer": "вечеряємо",
            "options": [
              "вечеряю",
              "вечеряєш",
              "вечеряє",
              "вечеряємо"
            ]
          },
          {
            "prompt": "Вони зазвичай ___ спати о одинадцятій годині ввечері. (to go to bed)",
            "answer": "лягають",
            "options": [
              "лягаю",
              "лягаєш",
              "лягає",
              "лягають"
            ]
          },
          {
            "prompt": "Я завжди ___ зуби двічі на день: вранці і ввечері. (to brush)",
            "answer": "чищу",
            "options": [
              "чищу",
              "чистиш",
              "чистить",
              "чистять"
            ]
          },
          {
            "prompt": "Він щоранку ___ у ванній перед сніданком. (to shave)",
            "answer": "голиться",
            "options": [
              "голюся",
              "голишся",
              "голиться",
              "голяться"
            ]
          },
          {
            "prompt": "Вона завжди дуже швидко ___ після важкого дня. (to fall asleep)",
            "answer": "засинає",
            "options": [
              "засинаю",
              "засинаєш",
              "засинає",
              "засинають"
            ]
          }
        ]
      },
      "subject": "language",
      "owner": "curricula-opus",
      "visibility": "public",
      "language": "uk",
      "difficultyLevel": "A1",
      "duration": 5,
      "tags": [],
      "createdAt": "2025-12-03T08:52:31.861Z",
      "modifiedAt": "2025-12-03T08:52:31.861Z"
    },
    {
      "id": "act-a1-25-unjumble",
      "type": "unjumble",
      "title": "Build the Sentence",
      "description": "Arrange the words in the correct order.",
      "content": {
        "type": "unjumble",
        "items": [
          {
            "words": [
              "прокидаюся",
              "о",
              "Я",
              "сьомій",
              "зазвичай",
              "годині",
              "кожен",
              "ранок"
            ],
            "answer": "Я зазвичай прокидаюся о сьомій годині кожен ранок.",
            "translation": "I usually wake up at 7 o'clock every morning."
          },
          {
            "words": [
              "вмивається",
              "Він",
              "потім",
              "швидко",
              "у",
              "ванній",
              "і",
              "одягається"
            ],
            "answer": "Потім він швидко вмивається у ванній і одягається.",
            "translation": "Then he quickly washes up in the bathroom and gets dressed."
          },
          {
            "words": [
              "снідає",
              "восьмій",
              "Вона",
              "о",
              "завжди",
              "на",
              "кухні",
              "годині"
            ],
            "answer": "Вона завжди снідає о восьмій годині на кухні.",
            "translation": "She always has breakfast at 8 o'clock in the kitchen."
          },
          {
            "words": [
              "з",
              "до",
              "працюю",
              "дев'ятої",
              "п'ятої",
              "Я",
              "щодня",
              "офісі",
              "у"
            ],
            "answer": "Я щодня працюю у офісі з дев'ятої до п'ятої.",
            "translation": "I work at the office every day from 9 to 5."
          },
          {
            "words": [
              "повертаємося",
              "додому",
              "Ми",
              "ввечері",
              "пізно",
              "дуже",
              "з",
              "роботи"
            ],
            "answer": "Ми повертаємося з роботи додому дуже пізно ввечері.",
            "translation": "We return home from work very late in the evening."
          },
          {
            "words": [
              "лягають",
              "Вони",
              "спати",
              "о",
              "одинадцятій",
              "зазвичай",
              "годині",
              "ввечері"
            ],
            "answer": "Вони зазвичай лягають спати о одинадцятій годині ввечері.",
            "translation": "They usually go to bed at 11 PM."
          },
          {
            "words": [
              "вранці",
              "чищу",
              "Я",
              "зуби",
              "завжди",
              "і",
              "ввечері",
              "двічі"
            ],
            "answer": "Я завжди чищу зуби двічі: вранці і ввечері.",
            "translation": "I always brush my teeth twice: in the morning and evening."
          },
          {
            "words": [
              "одягаюся",
              "Спочатку",
              "я",
              "потім",
              "снідаю",
              "швидко",
              "на",
              "кухні"
            ],
            "answer": "Спочатку я швидко одягаюся, потім снідаю на кухні.",
            "translation": "First I quickly get dressed, then I have breakfast in the kitchen."
          },
          {
            "words": [
              "швидко",
              "засинає",
              "Він",
              "зазвичай",
              "ввечері",
              "дуже",
              "після",
              "роботи"
            ],
            "answer": "Він зазвичай дуже швидко засинає ввечері після роботи.",
            "translation": "He usually falls asleep very quickly in the evening after work."
          },
          {
            "words": [
              "щодня",
              "снідаю",
              "Я",
              "о",
              "восьмій",
              "годині",
              "кухні",
              "на"
            ],
            "answer": "Я щодня снідаю о восьмій годині на кухні.",
            "translation": "I have breakfast every day at 8 o'clock in the kitchen."
          }
        ]
      },
      "subject": "language",
      "owner": "curricula-opus",
      "visibility": "public",
      "language": "uk",
      "difficultyLevel": "A1",
      "duration": 5,
      "tags": [],
      "createdAt": "2025-12-03T08:52:31.861Z",
      "modifiedAt": "2025-12-03T08:52:31.861Z"
    },
    {
      "id": "act-a1-25-matchup",
      "type": "match-up",
      "title": "Daily Routine Vocabulary",
      "description": "Match Ukrainian daily routine words to their English meanings.",
      "content": {
        "type": "match-up",
        "pairs": [
          {
            "left": "прокидатися",
            "right": "to wake up"
          },
          {
            "left": "вставати",
            "right": "to get up"
          },
          {
            "left": "вмиватися",
            "right": "to wash (face)"
          },
          {
            "left": "одягатися",
            "right": "to get dressed"
          },
          {
            "left": "снідати",
            "right": "to have breakfast"
          },
          {
            "left": "обідати",
            "right": "to have lunch"
          },
          {
            "left": "вечеряти",
            "right": "to have dinner"
          },
          {
            "left": "повертатися",
            "right": "to return"
          },
          {
            "left": "лягати спати",
            "right": "to go to bed"
          },
          {
            "left": "засинати",
            "right": "to fall asleep"
          }
        ],
        "shuffleRight": true
      },
      "subject": "language",
      "owner": "curricula-opus",
      "visibility": "public",
      "language": "uk",
      "difficultyLevel": "A1",
      "duration": 5,
      "tags": [],
      "createdAt": "2025-12-03T08:52:31.861Z",
      "modifiedAt": "2025-12-03T08:52:31.861Z"
    },
    {
      "id": "act-a1-25-quiz",
      "type": "quiz",
      "title": "Daily Routine Grammar",
      "description": "Choose the correct answer.",
      "content": {
        "type": "quiz",
        "questions": [
          {
            "question": "What does -ся at the end of verbs indicate?",
            "options": [
              "reflexive action (done to oneself)",
              "past tense",
              "future tense",
              "negative"
            ],
            "correctIndex": 0,
            "explanation": "-ся means \"oneself\" (from себе)"
          },
          {
            "question": "What is \"я прокидаюся\" in English?",
            "options": [
              "I wake up",
              "I get dressed",
              "I wash",
              "I return"
            ],
            "correctIndex": 0,
            "explanation": "прокидатися = to wake up"
          },
          {
            "question": "How do you say \"at 7 o'clock\"?",
            "options": [
              "о сьомій",
              "у сім",
              "на сьомій",
              "до сьомої"
            ],
            "correctIndex": 0,
            "explanation": "о + ordinal number in locative"
          },
          {
            "question": "What does \"щодня\" mean?",
            "options": [
              "every day",
              "sometimes",
              "never",
              "always"
            ],
            "correctIndex": 0,
            "explanation": "щодня = every day"
          },
          {
            "question": "What is \"спочатку\" in English?",
            "options": [
              "first, at first",
              "then",
              "finally",
              "later"
            ],
            "correctIndex": 0,
            "explanation": "спочатку = first"
          },
          {
            "question": "How do you say \"I brush my teeth\"?",
            "options": [
              "Я чищу зуби",
              "Я вмиваю зуби",
              "Я голю зуби",
              "Я миваю зуби"
            ],
            "correctIndex": 0,
            "explanation": "чистити зуби = to brush teeth"
          },
          {
            "question": "What does \"зазвичай\" mean?",
            "options": [
              "usually",
              "always",
              "never",
              "sometimes"
            ],
            "correctIndex": 0,
            "explanation": "зазвичай = usually"
          },
          {
            "question": "How do you say \"I work from 9 to 5\"?",
            "options": [
              "Я працюю з дев'ятої до п'ятої",
              "Я працюю о дев'ятій о п'ятій",
              "Я працюю у дев'ять до п'ять",
              "Я працюю від 9 до 5"
            ],
            "correctIndex": 0,
            "explanation": "з... до... + genitive of ordinal numbers"
          },
          {
            "question": "What is \"лягати спати\"?",
            "options": [
              "to go to bed",
              "to wake up",
              "to fall asleep",
              "to get up"
            ],
            "correctIndex": 0,
            "explanation": "лягати спати = to lie down to sleep"
          },
          {
            "question": "What does \"ввечері\" mean?",
            "options": [
              "in the evening",
              "in the morning",
              "at night",
              "during the day"
            ],
            "correctIndex": 0,
            "explanation": "ввечері = in the evening"
          }
        ],
        "shuffleQuestions": true,
        "shuffleOptions": true,
        "showCorrectAnswers": true
      },
      "subject": "language",
      "owner": "curricula-opus",
      "visibility": "public",
      "language": "uk",
      "difficultyLevel": "A1",
      "duration": 5,
      "tags": [],
      "createdAt": "2025-12-03T08:52:31.861Z",
      "modifiedAt": "2025-12-03T08:52:31.861Z"
    },
    {
      "id": "act-a1-25-truefalse",
      "type": "true-false",
      "title": "True or False?",
      "description": "Determine if each statement is true or false.",
      "content": {
        "type": "true-false",
        "statements": []
      },
      "subject": "language",
      "owner": "curricula-opus",
      "visibility": "public",
      "language": "uk",
      "difficultyLevel": "A1",
      "duration": 5,
      "tags": [],
      "createdAt": "2025-12-03T08:52:31.861Z",
      "modifiedAt": "2025-12-03T08:52:31.861Z"
    },
    {
      "id": "act-a1-25-groupsort",
      "type": "group-sort",
      "title": "Daily Routine Categories",
      "description": "Sort these activities by time of day.",
      "content": {
        "type": "group-sort",
        "groups": [
          {
            "id": "morning-activities",
            "name": "Morning Activities",
            "items": [
              "прокидатися (wake up)",
              "вмиватися (wash)",
              "снідати (have breakfast)",
              "одягатися (get dressed)"
            ]
          },
          {
            "id": "daytime-activities",
            "name": "Daytime Activities",
            "items": [
              "працювати (work)",
              "обідати (have lunch)",
              "виходити з дому (leave home)"
            ]
          },
          {
            "id": "evening-activities",
            "name": "Evening Activities",
            "items": [
              "повертатися (return)",
              "вечеряти (have dinner)",
              "лягати спати (go to bed)",
              "засинати (fall asleep)"
            ]
          }
        ],
        "shuffleItems": true
      },
      "subject": "language",
      "owner": "curricula-opus",
      "visibility": "public",
      "language": "uk",
      "difficultyLevel": "A1",
      "duration": 5,
      "tags": [],
      "createdAt": "2025-12-03T08:52:31.861Z",
      "modifiedAt": "2025-12-03T08:52:31.861Z"
    }
  ],
  "vocabulary": {
    "moduleId": "mod-uk-A1-25",
    "level": "A1",
    "phase": "A1.3",
    "wordCount": 19,
    "newWordCount": 19,
    "reviewWordCount": 0,
    "transliterationMode": "full",
    "words": [
      {
        "id": "v-prokydatysya-25-0",
        "uk": "прокидатися",
        "en": "to wake up",
        "pos": "verb",
        "ipa": "/prɔkɪˈdɑtɪsʲɑ/",
        "note": "Reflexive",
        "isNew": true,
        "firstModule": 25
      },
      {
        "id": "v-vstavaty-25-1",
        "uk": "вставати",
        "en": "to get up",
        "pos": "verb",
        "ipa": "/vstɑˈvɑtɪ/",
        "note": "встаю, встаєш",
        "isNew": true,
        "firstModule": 25
      },
      {
        "id": "v-vmyvatysya-25-2",
        "uk": "вмиватися",
        "en": "to wash (face)",
        "pos": "verb",
        "ipa": "/vmɪˈvɑtɪsʲɑ/",
        "note": "Reflexive",
        "isNew": true,
        "firstModule": 25
      },
      {
        "id": "v-odyahatysya-25-3",
        "uk": "одягатися",
        "en": "to get dressed",
        "pos": "verb",
        "ipa": "/ɔˈdʲɑɦɑtɪsʲɑ/",
        "note": "Reflexive",
        "isNew": true,
        "firstModule": 25
      },
      {
        "id": "v-rozdyahatysya-25-4",
        "uk": "роздягатися",
        "en": "to undress",
        "pos": "verb",
        "ipa": "/rɔzˈdʲɑɦɑtɪsʲɑ/",
        "note": "Reflexive",
        "isNew": true,
        "firstModule": 25
      },
      {
        "id": "v-snidaty-25-5",
        "uk": "снідати",
        "en": "to have breakfast",
        "pos": "verb",
        "ipa": "/snʲiˈdɑtɪ/",
        "isNew": true,
        "firstModule": 25
      },
      {
        "id": "v-obidaty-25-6",
        "uk": "обідати",
        "en": "to have lunch",
        "pos": "verb",
        "ipa": "/ɔˈbʲidɑtɪ/",
        "isNew": true,
        "firstModule": 25
      },
      {
        "id": "v-vecheryaty-25-7",
        "uk": "вечеряти",
        "en": "to have dinner",
        "pos": "verb",
        "ipa": "/vɛtʃɛˈrʲɑtɪ/",
        "isNew": true,
        "firstModule": 25
      },
      {
        "id": "v-vykhodyty-25-8",
        "uk": "виходити",
        "en": "to go out, leave",
        "pos": "verb",
        "ipa": "/vɪxɔˈdɪtɪ/",
        "isNew": true,
        "firstModule": 25
      },
      {
        "id": "v-povertatysya-25-9",
        "uk": "повертатися",
        "en": "to return",
        "pos": "verb",
        "ipa": "/pɔvɛrˈtɑtɪsʲɑ/",
        "note": "Reflexive",
        "isNew": true,
        "firstModule": 25
      },
      {
        "id": "v-lyahaty-25-10",
        "uk": "лягати",
        "en": "to lie down",
        "pos": "verb",
        "ipa": "/lʲɑˈɦɑtɪ/",
        "note": "лягати спати",
        "isNew": true,
        "firstModule": 25
      },
      {
        "id": "v-zasynaty-25-11",
        "uk": "засинати",
        "en": "to fall asleep",
        "pos": "verb",
        "ipa": "/zɑsɪˈnɑtɪ/",
        "isNew": true,
        "firstModule": 25
      },
      {
        "id": "v-holytysya-25-12",
        "uk": "голитися",
        "en": "to shave",
        "pos": "verb",
        "ipa": "/ɦɔˈlɪtɪsʲɑ/",
        "note": "Reflexive",
        "isNew": true,
        "firstModule": 25
      },
      {
        "id": "v-chystyty-25-13",
        "uk": "чистити",
        "en": "to clean, brush",
        "pos": "verb",
        "ipa": "/ˈtʃɪstɪtɪ/",
        "note": "чистити зуби",
        "isNew": true,
        "firstModule": 25
      },
      {
        "id": "v-dush-25-14",
        "uk": "душ",
        "en": "shower",
        "pos": "noun",
        "ipa": "/duʃ/",
        "gender": "m",
        "note": "приймати душ",
        "isNew": true,
        "firstModule": 25
      },
      {
        "id": "v-zuby-25-15",
        "uk": "зуби",
        "en": "teeth",
        "pos": "noun",
        "ipa": "/ˈzubɪ/",
        "note": "Singular: зуб",
        "isNew": true,
        "firstModule": 25
      },
      {
        "id": "v-spochatku-25-16",
        "uk": "спочатку",
        "en": "first, at first",
        "pos": "adv",
        "ipa": "/spɔˈtʃɑtku/",
        "isNew": true,
        "firstModule": 25
      },
      {
        "id": "v-zazvychay-25-17",
        "uk": "зазвичай",
        "en": "usually",
        "pos": "adv",
        "ipa": "/zɑˈzvɪtʃɑj/",
        "isNew": true,
        "firstModule": 25
      },
      {
        "id": "v-shchodnya-25-18",
        "uk": "щодня",
        "en": "every day",
        "pos": "adv",
        "ipa": "/ʃtʃɔˈdnʲɑ/",
        "isNew": true,
        "firstModule": 25
      }
    ]
  }
}