{
  "track": "c1-bio",
  "slug": "yurii-lypa",
  "mode": "v3",
  "phases": {
    "v3-A": {
      "status": "complete",
      "ts": "2026-02-19T20:03:34Z",
      "task_id": "v3-yurii-lypa-pA",
      "mode": "full"
    },
    "v3-B": {
      "status": "complete",
      "ts": "2026-02-27T00:51:33Z"
    },
    "v3-C": {
      "status": "complete",
      "ts": "2026-02-27T00:53:16Z",
      "task_id": "v3-yurii-lypa-pC"
    },
    "v3-audit": {
      "status": "complete",
      "ts": "2026-02-27T00:53:17Z",
      "attempts": 0,
      "note": "auto-fix"
    }
  }
}